Metadata-Version: 2.1
Name: AbInbevCase
Version: 1.0.0
Summary: AbInbev Challenge Project for Fuel Efficiency
Author-email: Heigon Soldera <heigonsoldera77@gmail.com>
Classifier: Programming Language :: Python :: 3
Classifier: License :: OSI Approved :: MIT License
Classifier: Operating System :: OS Independent
Requires-Python: >=3.8
